ui24rsc/__init__.py
ui24rsc/__main__.py
ui24rsc/cli.py
ui24rsc/default-init.yml
ui24rsc-1.0.4.dist-info/LICENSE
ui24rsc-1.0.4.dist-info/METADATA
ui24rsc-1.0.4.dist-info/WHEEL
ui24rsc-1.0.4.dist-info/entry_points.txt
ui24rsc-1.0.4.dist-info/top_level.txt
ui24rsc-1.0.4.dist-info/RECORD
