Metadata-Version: 2.1
Name: ui24rsc
Version: 1.0.4
Summary: Ui24R Snapshot Converter
Home-page: https://github.com/dmotte/ui24rsc
Author: dmotte
License: MIT
Keywords: soundcraft ui24r yaml converter diff json tree command snapshot yml mixer dots structured full dotted dotted-format
Classifier: Intended Audience :: End Users/Desktop
Classifier: Environment :: Console
Classifier: Natural Language :: English
Classifier: License :: OSI Approved :: MIT License
Classifier: Programming Language :: Python
Classifier: Programming Language :: Python :: 3
Classifier: Programming Language :: Python :: 3 :: Only
Classifier: Programming Language :: Python :: 3.9
Classifier: Topic :: Terminals
Classifier: Topic :: Utilities
Requires-Python: >=3.9.1
License-File: LICENSE
Requires-Dist: PyYAML >=5.4.1
